discord_template/__init__.py
discord_template/__main__.py
discord_template/startup
discord_template/env/config
discord_template/env/main
discord_template/env/ext/moderation.py
discord_template/env/ext/ping.py
discordtemplate-1.1.3.dist-info/LICENSE
discordtemplate-1.1.3.dist-info/METADATA
discordtemplate-1.1.3.dist-info/WHEEL
discordtemplate-1.1.3.dist-info/entry_points.txt
discordtemplate-1.1.3.dist-info/top_level.txt
discordtemplate-1.1.3.dist-info/RECORD
