Metadata-Version: 2.1
Name: discordtemplate
Version: 1.1.3
Summary: 🔹 A new and enhanced boilerplate template for discord.py
Home-page: https://github.com/znqi/discordtemplate/
Author: Zenqi
License: MIT
Platform: UNKNOWN
Classifier: Development Status :: 4 - Beta
Classifier: License :: OSI Approved :: MIT License
Classifier: Programming Language :: Python
Requires-Python: >=3.5
Requires-Dist: jinja2
Requires-Dist: InquirerPy
Requires-Dist: tabulate
Requires-Dist: discord.py
